LICENSE
README.md
setup.cfg
setup.py
ivao/__init__.py
ivao.egg-info/PKG-INFO
ivao.egg-info/SOURCES.txt
ivao.egg-info/dependency_links.txt
ivao.egg-info/requires.txt
ivao.egg-info/top_level.txt