Metadata-Version: 2.1
Name: ivao
Version: 2.1
Summary: IVAO WhazzupAPI for Python
Author: Chawalwit Akarajirathanachot
Author-email: meck22772@gmail.com
License: MIT
License-File: LICENSE
